pykvsdb.py
pykvsdb-0.1.1.dist-info/LICENSE
pykvsdb-0.1.1.dist-info/WHEEL
pykvsdb-0.1.1.dist-info/METADATA
pykvsdb-0.1.1.dist-info/RECORD
