Metadata-Version: 2.1
Name: pykvsdb
Version: 0.1.1
Summary: A key-value store database written from the ground-up with speed in mind.
License: Apache-2.0
Author: DrgnFireYellow
Author-email: 86269995+DrgnFireYellow@users.noreply.github.com
Requires-Python: >=3.9,<4.0
Classifier: License :: OSI Approved :: Apache Software License
Classifier: Programming Language :: Python :: 3
Classifier: Programming Language :: Python :: 3.9
Classifier: Programming Language :: Python :: 3.10
